Metadata-Version: 1.0
Name: mergefier
Version: 0.1.15
Summary: You use this to merge your pull requests.
Home-page: http://github.com/enkelbr/mergefier
Author: Gustavo Maia
Author-email: gurumaia@gmail.com
License: GPL
Platform: UNKNOWN
